LICENSE
discogs_alert/__init__.py
discogs_alert/__main__.py
discogs_alert/alert/__init__.py
discogs_alert/alert/base.py
discogs_alert/alert/pushbullet.py
discogs_alert/alert/telegram.py
discogs_alert/client.py
discogs_alert/entities.py
discogs_alert/loop.py
discogs_alert/scrape.py
discogs_alert/util/__init__.py
discogs_alert/util/click.py
discogs_alert/util/constants.py
discogs_alert/util/currency.py
discogs_alert/util/system.py
discogs_alert-0.0.21.dist-info/LICENSE
discogs_alert-0.0.21.dist-info/METADATA
discogs_alert-0.0.21.dist-info/WHEEL
discogs_alert-0.0.21.dist-info/RECORD
