Metadata-Version: 2.1
Name: discogs_alert
Version: 0.0.21
Summary: Configurable, real-time alerts for your discogs wantlist
Home-page: https://github.com/michaelhball/discogs_alert
License: MIT
Keywords: discogs,dig,digger
Author: mhsb
Author-email: michael.h.s.ball@gmail.com
Requires-Python: >=3.8,<4.0
Classifier: License :: OSI Approved :: MIT License
Classifier: Programming Language :: Python :: 3
Classifier: Programming Language :: Python :: 3.8
Classifier: Programming Language :: Python :: 3.9
Classifier: Programming Language :: Python :: 3.10
Classifier: Programming Language :: Python :: 3.11
Classifier: Programming Language :: Python :: 3.12
Requires-Dist: beautifulsoup4 (>=4.11.2,<5.0.0)
Requires-Dist: click (>=8.1.3,<9.0.0)
Requires-Dist: dacite (>=1.8.0,<2.0.0)
Requires-Dist: fake-useragent (>=1.1.1,<2.0.0)
Requires-Dist: freecurrencyapi (>=0.1.0,<0.2.0)
Requires-Dist: pre-commit (>=2.20.0,<3.0.0)
Requires-Dist: psutil (>=5.9.7,<6.0.0)
Requires-Dist: requests (>=2.28.2,<3.0.0)
Requires-Dist: ruff (>=0.0.253,<0.0.254)
Requires-Dist: schedule (>=1.1.0,<2.0.0)
Requires-Dist: selenium (>=4.14.0,<5.0.0)
Requires-Dist: tox (>=3,<4) ; python_version < "3.8"
Requires-Dist: tox (>=4.4.5,<5.0.0) ; python_version >= "3.8"
Requires-Dist: webdriver-manager (>=4,<5)
Project-URL: Repository, https://github.com/michaelhball/discogs_alert
